{"packages":{"sebastian/global-state":{"1.0.0":{"name":"sebastian/global-state","description":"Snapshotting of global state","keywords":["global state"],"homepage":"http://www.github.com/sebastianbergmann/global-state","version":"1.0.0","version_normalized":"1.0.0.0","license":["BSD-3-Clause"],"authors":[{"name":"Sebastian Bergmann","email":"sebastian@phpunit.de"}],"source":{"type":"git","url":"https://github.com/sebastianbergmann/global-state.git","reference":"c7428acdb62ece0a45e6306f1ae85e1c05b09c01"},"dist":{"type":"zip","url":"https://api.github.com/repos/sebastianbergmann/global-state/zipball/c7428acdb62ece0a45e6306f1ae85e1c05b09c01","reference":"c7428acdb62ece0a45e6306f1ae85e1c05b09c01","shasum":""},"type":"library","time":"2014-10-06T09:23:50+00:00","autoload":{"classmap":["src/"]},"extra":{"branch-alias":{"dev-master":"1.0-dev"}},"require":{"php":">=5.3.3"},"require-dev":{"phpunit/phpunit":"~4.2"},"suggest":{"ext-uopz":"*"},"uid":281008},"1.1.0":{"name":"sebastian/global-state","description":"Snapshotting of global state","keywords":["global state"],"homepage":"http://www.github.com/sebastianbergmann/global-state","version":"1.1.0","version_normalized":"1.1.0.0","license":["BSD-3-Clause"],"authors":[{"name":"Sebastian Bergmann","email":"sebastian@phpunit.de"}],"source":{"type":"git","url":"https://github.com/sebastianbergmann/global-state.git","reference":"23af31f402993cfd94e99cbc4b782e9a78eb0e97"},"dist":{"type":"zip","url":"https://api.github.com/repos/sebastianbergmann/global-state/zipball/23af31f402993cfd94e99cbc4b782e9a78eb0e97","reference":"23af31f402993cfd94e99cbc4b782e9a78eb0e97","shasum":""},"type":"library","time":"2015-06-21T15:11:22+00:00","autoload":{"classmap":["src/"]},"extra":{"branch-alias":{"dev-master":"1.0-dev"}},"require":{"php":">=5.3.3"},"require-dev":{"phpunit/phpunit":"~4.2"},"suggest":{"ext-uopz":"*"},"uid":545519},"1.1.1":{"name":"sebastian/global-state","description":"Snapshotting of global state","keywords":["global state"],"homepage":"http://www.github.com/sebastianbergmann/global-state","version":"1.1.1","version_normalized":"1.1.1.0","license":["BSD-3-Clause"],"authors":[{"name":"Sebastian Bergmann","email":"sebastian@phpunit.de"}],"source":{"type":"git","url":"https://github.com/sebastianbergmann/global-state.git","reference":"bc37d50fea7d017d3d340f230811c9f1d7280af4"},"dist":{"type":"zip","url":"https://api.github.com/repos/sebastianbergmann/global-state/zipball/bc37d50fea7d017d3d340f230811c9f1d7280af4","reference":"bc37d50fea7d017d3d340f230811c9f1d7280af4","shasum":""},"type":"library","time":"2015-10-12T03:26:01+00:00","autoload":{"classmap":["src/"]},"extra":{"branch-alias":{"dev-master":"1.0-dev"}},"require":{"php":">=5.3.3"},"require-dev":{"phpunit/phpunit":"~4.2"},"suggest":{"ext-uopz":"*"},"uid":547832},"1.1.x-dev":{"name":"sebastian/global-state","description":"Snapshotting of global state","keywords":["global state"],"homepage":"http://www.github.com/sebastianbergmann/global-state","version":"1.1.x-dev","version_normalized":"1.1.9999999.9999999-dev","license":["BSD-3-Clause"],"authors":[{"name":"Sebastian Bergmann","email":"sebastian@phpunit.de"}],"source":{"type":"git","url":"https://github.com/sebastianbergmann/global-state.git","reference":"cea85a84b00f2795341ebbbca4fa396347f2494e"},"dist":{"type":"zip","url":"https://api.github.com/repos/sebastianbergmann/global-state/zipball/cea85a84b00f2795341ebbbca4fa396347f2494e","reference":"cea85a84b00f2795341ebbbca4fa396347f2494e","shasum":""},"type":"library","time":"2017-02-23T14:11:06+00:00","autoload":{"classmap":["src/"]},"extra":{"branch-alias":{"dev-master":"1.0-dev"}},"require":{"php":">=5.3.3"},"require-dev":{"phpunit/phpunit":"~4.2|~5.0"},"suggest":{"ext-uopz":"*"},"uid":1123697},"2.0.0":{"name":"sebastian/global-state","description":"Snapshotting of global state","keywords":["global state"],"homepage":"http://www.github.com/sebastianbergmann/global-state","version":"2.0.0","version_normalized":"2.0.0.0","license":["BSD-3-Clause"],"authors":[{"name":"Sebastian Bergmann","email":"sebastian@phpunit.de"}],"source":{"type":"git","url":"https://github.com/sebastianbergmann/global-state.git","reference":"e8ba02eed7bbbb9e59e43dedd3dddeff4a56b0c4"},"dist":{"type":"zip","url":"https://api.github.com/repos/sebastianbergmann/global-state/zipball/e8ba02eed7bbbb9e59e43dedd3dddeff4a56b0c4","reference":"e8ba02eed7bbbb9e59e43dedd3dddeff4a56b0c4","shasum":""},"type":"library","time":"2017-04-27T15:39:26+00:00","autoload":{"classmap":["src/"]},"extra":{"branch-alias":{"dev-master":"2.0-dev"}},"require":{"php":"^7.0"},"require-dev":{"phpunit/phpunit":"^6.0"},"suggest":{"ext-uopz":"*"},"uid":1365095},"3.0.0":{"name":"sebastian/global-state","description":"Snapshotting of global state","keywords":["global state"],"homepage":"http://www.github.com/sebastianbergmann/global-state","version":"3.0.0","version_normalized":"3.0.0.0","license":["BSD-3-Clause"],"authors":[{"name":"Sebastian Bergmann","email":"sebastian@phpunit.de"}],"source":{"type":"git","url":"https://github.com/sebastianbergmann/global-state.git","reference":"edf8a461cf1d4005f19fb0b6b8b95a9f7fa0adc4"},"dist":{"type":"zip","url":"https://api.github.com/repos/sebastianbergmann/global-state/zipball/edf8a461cf1d4005f19fb0b6b8b95a9f7fa0adc4","reference":"edf8a461cf1d4005f19fb0b6b8b95a9f7fa0adc4","shasum":""},"type":"library","time":"2019-02-01T05:30:01+00:00","autoload":{"classmap":["src/"]},"extra":{"branch-alias":{"dev-master":"3.0-dev"}},"require":{"php":"^7.2","sebastian/object-reflector":"^1.1.1","sebastian/recursion-context":"^3.0"},"require-dev":{"ext-dom":"*","phpunit/phpunit":"^8.0"},"suggest":{"ext-uopz":"*"},"uid":2730887},"3.0.1":{"name":"sebastian/global-state","description":"Snapshotting of global state","keywords":["global state"],"homepage":"http://www.github.com/sebastianbergmann/global-state","version":"3.0.1","version_normalized":"3.0.1.0","license":["BSD-3-Clause"],"authors":[{"name":"Sebastian Bergmann","email":"sebastian@phpunit.de"}],"source":{"type":"git","url":"https://github.com/sebastianbergmann/global-state.git","reference":"474fb9edb7ab891665d3bfc6317f42a0a150454b"},"dist":{"type":"zip","url":"https://api.github.com/repos/sebastianbergmann/global-state/zipball/474fb9edb7ab891665d3bfc6317f42a0a150454b","reference":"474fb9edb7ab891665d3bfc6317f42a0a150454b","shasum":""},"type":"library","funding":[{"url":"https://github.com/sebastianbergmann","type":"github"}],"time":"2020-11-30T07:43:24+00:00","autoload":{"classmap":["src/"]},"extra":{"branch-alias":{"dev-master":"3.0-dev"}},"require":{"php":">=7.2","sebastian/object-reflector":"^1.1.1","sebastian/recursion-context":"^3.0"},"require-dev":{"ext-dom":"*","phpunit/phpunit":"^8.0"},"suggest":{"ext-uopz":"*"},"uid":4696220},"3.0.x-dev":{"name":"sebastian/global-state","description":"Snapshotting of global state","keywords":["global state"],"homepage":"http://www.github.com/sebastianbergmann/global-state","version":"3.0.x-dev","version_normalized":"3.0.9999999.9999999-dev","license":["BSD-3-Clause"],"authors":[{"name":"Sebastian Bergmann","email":"sebastian@phpunit.de"}],"source":{"type":"git","url":"https://github.com/sebastianbergmann/global-state.git","reference":"474fb9edb7ab891665d3bfc6317f42a0a150454b"},"dist":{"type":"zip","url":"https://api.github.com/repos/sebastianbergmann/global-state/zipball/474fb9edb7ab891665d3bfc6317f42a0a150454b","reference":"474fb9edb7ab891665d3bfc6317f42a0a150454b","shasum":""},"type":"library","funding":[{"url":"https://github.com/sebastianbergmann","type":"github"}],"time":"2020-11-30T07:43:24+00:00","autoload":{"classmap":["src/"]},"extra":{"branch-alias":{"dev-master":"3.0-dev"}},"require":{"php":">=7.2","sebastian/object-reflector":"^1.1.1","sebastian/recursion-context":"^3.0"},"require-dev":{"ext-dom":"*","phpunit/phpunit":"^8.0"},"suggest":{"ext-uopz":"*"},"uid":4696219},"4.0.0":{"name":"sebastian/global-state","description":"Snapshotting of global state","keywords":["global state"],"homepage":"http://www.github.com/sebastianbergmann/global-state","version":"4.0.0","version_normalized":"4.0.0.0","license":["BSD-3-Clause"],"authors":[{"name":"Sebastian Bergmann","email":"sebastian@phpunit.de"}],"source":{"type":"git","url":"https://github.com/sebastianbergmann/global-state.git","reference":"bdb1e7c79e592b8c82cb1699be3c8743119b8a72"},"dist":{"type":"zip","url":"https://api.github.com/repos/sebastianbergmann/global-state/zipball/bdb1e7c79e592b8c82cb1699be3c8743119b8a72","reference":"bdb1e7c79e592b8c82cb1699be3c8743119b8a72","shasum":""},"type":"library","time":"2020-02-07T06:11:37+00:00","autoload":{"classmap":["src/"]},"extra":{"branch-alias":{"dev-master":"4.0-dev"}},"require":{"php":"^7.3","sebastian/object-reflector":"^2.0","sebastian/recursion-context":"^4.0"},"require-dev":{"ext-dom":"*","phpunit/phpunit":"^9.0"},"suggest":{"ext-uopz":"*"},"uid":3592305},"5.0.0":{"name":"sebastian/global-state","description":"Snapshotting of global state","keywords":["global state"],"homepage":"http://www.github.com/sebastianbergmann/global-state","version":"5.0.0","version_normalized":"5.0.0.0","license":["BSD-3-Clause"],"authors":[{"name":"Sebastian Bergmann","email":"sebastian@phpunit.de"}],"source":{"type":"git","url":"https://github.com/sebastianbergmann/global-state.git","reference":"22ae663c951bdc39da96603edc3239ed3a299097"},"dist":{"type":"zip","url":"https://api.github.com/repos/sebastianbergmann/global-state/zipball/22ae663c951bdc39da96603edc3239ed3a299097","reference":"22ae663c951bdc39da96603edc3239ed3a299097","shasum":""},"type":"library","funding":[{"url":"https://github.com/sebastianbergmann","type":"github"}],"time":"2020-08-07T04:09:03+00:00","autoload":{"classmap":["src/"]},"extra":{"branch-alias":{"dev-master":"5.0-dev"}},"require":{"php":"^7.3 || ^8.0","sebastian/object-reflector":"^2.0","sebastian/recursion-context":"^4.0"},"require-dev":{"ext-dom":"*","phpunit/phpunit":"^9.3"},"suggest":{"ext-uopz":"*"},"uid":4337175},"5.0.1":{"name":"sebastian/global-state","description":"Snapshotting of global state","keywords":["global state"],"homepage":"http://www.github.com/sebastianbergmann/global-state","version":"5.0.1","version_normalized":"5.0.1.0","license":["BSD-3-Clause"],"authors":[{"name":"Sebastian Bergmann","email":"sebastian@phpunit.de"}],"source":{"type":"git","url":"https://github.com/sebastianbergmann/global-state.git","reference":"ea779cb749a478b22a2564ac41cd7bda79c78dc7"},"dist":{"type":"zip","url":"https://api.github.com/repos/sebastianbergmann/global-state/zipball/ea779cb749a478b22a2564ac41cd7bda79c78dc7","reference":"ea779cb749a478b22a2564ac41cd7bda79c78dc7","shasum":""},"type":"library","funding":[{"url":"https://github.com/sebastianbergmann","type":"github"}],"time":"2020-09-28T05:54:06+00:00","autoload":{"classmap":["src/"]},"extra":{"branch-alias":{"dev-master":"5.0-dev"}},"require":{"php":">=7.3","sebastian/object-reflector":"^2.0","sebastian/recursion-context":"^4.0"},"require-dev":{"ext-dom":"*","phpunit/phpunit":"^9.3"},"suggest":{"ext-uopz":"*"},"uid":4491642},"5.0.2":{"name":"sebastian/global-state","description":"Snapshotting of global state","keywords":["global state"],"homepage":"http://www.github.com/sebastianbergmann/global-state","version":"5.0.2","version_normalized":"5.0.2.0","license":["BSD-3-Clause"],"authors":[{"name":"Sebastian Bergmann","email":"sebastian@phpunit.de"}],"source":{"type":"git","url":"https://github.com/sebastianbergmann/global-state.git","reference":"a90ccbddffa067b51f574dea6eb25d5680839455"},"dist":{"type":"zip","url":"https://api.github.com/repos/sebastianbergmann/global-state/zipball/a90ccbddffa067b51f574dea6eb25d5680839455","reference":"a90ccbddffa067b51f574dea6eb25d5680839455","shasum":""},"type":"library","funding":[{"url":"https://github.com/sebastianbergmann","type":"github"}],"time":"2020-10-26T15:55:19+00:00","autoload":{"classmap":["src/"]},"extra":{"branch-alias":{"dev-master":"5.0-dev"}},"require":{"php":">=7.3","sebastian/object-reflector":"^2.0","sebastian/recursion-context":"^4.0"},"require-dev":{"ext-dom":"*","phpunit/phpunit":"^9.3"},"suggest":{"ext-uopz":"*"},"uid":4583948},"5.0.3":{"name":"sebastian/global-state","description":"Snapshotting of global state","keywords":["global state"],"homepage":"http://www.github.com/sebastianbergmann/global-state","version":"5.0.3","version_normalized":"5.0.3.0","license":["BSD-3-Clause"],"authors":[{"name":"Sebastian Bergmann","email":"sebastian@phpunit.de"}],"source":{"type":"git","url":"https://github.com/sebastianbergmann/global-state.git","reference":"23bd5951f7ff26f12d4e3242864df3e08dec4e49"},"dist":{"type":"zip","url":"https://api.github.com/repos/sebastianbergmann/global-state/zipball/23bd5951f7ff26f12d4e3242864df3e08dec4e49","reference":"23bd5951f7ff26f12d4e3242864df3e08dec4e49","shasum":""},"type":"library","funding":[{"url":"https://github.com/sebastianbergmann","type":"github"}],"time":"2021-06-11T13:31:12+00:00","autoload":{"classmap":["src/"]},"extra":{"branch-alias":{"dev-master":"5.0-dev"}},"require":{"php":">=7.3","sebastian/object-reflector":"^2.0","sebastian/recursion-context":"^4.0"},"require-dev":{"ext-dom":"*","phpunit/phpunit":"^9.3"},"suggest":{"ext-uopz":"*"},"uid":5281341},"dev-issue-12":{"name":"sebastian/global-state","description":"Snapshotting of global state","keywords":["global state"],"homepage":"http://www.github.com/sebastianbergmann/global-state","version":"dev-issue-12","version_normalized":"dev-issue-12","license":["BSD-3-Clause"],"authors":[{"name":"Sebastian Bergmann","email":"sebastian@phpunit.de"}],"source":{"type":"git","url":"https://github.com/sebastianbergmann/global-state.git","reference":"f302da795894ad40fa3d2ea52b73d9267f4cd160"},"dist":{"type":"zip","url":"https://api.github.com/repos/sebastianbergmann/global-state/zipball/f302da795894ad40fa3d2ea52b73d9267f4cd160","reference":"f302da795894ad40fa3d2ea52b73d9267f4cd160","shasum":""},"type":"library","time":"2017-04-27T18:43:52+00:00","autoload":{"classmap":["src/"]},"extra":{"branch-alias":{"dev-master":"2.0-dev"}},"require":{"php":"^7.0","sebastian/object-enumerator":"^3.0.2"},"require-dev":{"phpunit/phpunit":"^6.0"},"suggest":{"ext-uopz":"*"},"uid":1365375},"dev-master":{"name":"sebastian/global-state","description":"Snapshotting of global state","keywords":["global state"],"homepage":"http://www.github.com/sebastianbergmann/global-state","version":"dev-master","version_normalized":"9999999-dev","license":["BSD-3-Clause"],"authors":[{"name":"Sebastian Bergmann","email":"sebastian@phpunit.de"}],"source":{"type":"git","url":"https://github.com/sebastianbergmann/global-state.git","reference":"23bd5951f7ff26f12d4e3242864df3e08dec4e49"},"dist":{"type":"zip","url":"https://api.github.com/repos/sebastianbergmann/global-state/zipball/23bd5951f7ff26f12d4e3242864df3e08dec4e49","reference":"23bd5951f7ff26f12d4e3242864df3e08dec4e49","shasum":""},"type":"library","funding":[{"url":"https://github.com/sebastianbergmann","type":"github"}],"time":"2021-06-11T13:31:12+00:00","autoload":{"classmap":["src/"]},"extra":{"branch-alias":{"dev-master":"5.0-dev"}},"default-branch":true,"require":{"sebastian/object-reflector":"^2.0","sebastian/recursion-context":"^4.0","php":">=7.3"},"require-dev":{"ext-dom":"*","phpunit/phpunit":"^9.3"},"suggest":{"ext-uopz":"*"},"uid":4004503}}}}